[
  {
    "inputs": [],
    "stateMutability": "payable",
    "type": "constructor"
  },
  {
    "inputs": [
      {
        "internalType": "address",
        "name": "target",
        "type": "address"
      }
    ],
    "name": "AddressEmptyCode",
    "type": "error"
  },
  {
    "inputs": [],
    "name": "AddressZeroDetected",
    "type": "error"
  },
  {
    "inputs": [],
    "name": "AlreadyRegistered",
    "type": "error"
  },
  {
    "inputs": [],
    "name": "AlreadyVerified",
    "type": "error"
  },
  {
    "inputs": [],
    "name": "EmptyAttendeesList",
    "type": "error"
  },
  {
    "inputs": [],
    "name": "EmptyTitleOrDescription",
    "type": "error"
  },
  {
    "inputs": [],
    "name": "EventDoesNotExist",
    "type": "error"
  },
  {
    "inputs": [],
    "name": "EventHasEnded",
    "type": "error"
  },
  {
    "inputs": [],
    "name": "EventNotEnded",
    "type": "error"
  },
  {
    "inputs": [],
    "name": "EventNotStarted",
    "type": "error"
  },
  {
    "inputs": [],
    "name": "ExpectedAttendeesIsTooLow",
    "type": "error"
  },
  {
    "inputs": [],
    "name": "FailedCall",
    "type": "error"
  },
  {
    "inputs": [],
    "name": "FreeTicketForFreeEventOnly",
    "type": "error"
  },
  {
    "inputs": [],
    "name": "InvalidDates",
    "type": "error"
  },
  {
    "inputs": [],
    "name": "InvalidTicketFee",
    "type": "error"
  },
  {
    "inputs": [],
    "name": "NoRevenueToRelease",
    "type": "error"
  },
  {
    "inputs": [],
    "name": "NotEventOrganizer",
    "type": "error"
  },
  {
    "inputs": [],
    "name": "NotRegisteredForEvent",
    "type": "error"
  },
  {
    "inputs": [],
    "name": "OnlyOrganiserCanCreateTicket",
    "type": "error"
  },
  {
    "inputs": [],
    "name": "OnlyOwnerCanRelease",
    "type": "error"
  },
  {
    "inputs": [],
    "name": "ReentrancyGuardReentrantCall",
    "type": "error"
  },
  {
    "inputs": [],
    "name": "RegistrationHasClosed",
    "type": "error"
  },
  {
    "inputs": [],
    "name": "RegularTicketMustCostLessThanVipTicket",
    "type": "error"
  },
  {
    "inputs": [],
    "name": "RevenueAlreadyReleased",
    "type": "error"
  },
  {
    "inputs": [],
    "name": "VipFeeTooLow",
    "type": "error"
  },
  {
    "inputs": [],
    "name": "YouCanNotCreateThisTypeOfTicketForThisEvent",
    "type": "error"
  },
  {
    "anonymous": false,
    "inputs": [
      {
        "indexed": true,
        "internalType": "uint256",
        "name": "_eventId",
        "type": "uint256"
      },
      {
        "indexed": true,
        "internalType": "address",
        "name": "_attendee",
        "type": "address"
      },
      {
        "indexed": false,
        "internalType": "uint256",
        "name": "_verificationTime",
        "type": "uint256"
      }
    ],
    "name": "AttendeeVerified",
    "type": "event"
  },
  {
    "anonymous": false,
    "inputs": [
      {
        "indexed": true,
        "internalType": "address",
        "name": "_from",
        "type": "address"
      },
      {
        "indexed": false,
        "internalType": "uint256",
        "name": "_amount",
        "type": "uint256"
      }
    ],
    "name": "EtherReceived",
    "type": "event"
  },
  {
    "anonymous": false,
    "inputs": [
      {
        "indexed": true,
        "internalType": "address",
        "name": "_organiser",
        "type": "address"
      },
      {
        "indexed": true,
        "internalType": "uint256",
        "name": "_eventId",
        "type": "uint256"
      },
      {
        "indexed": false,
        "internalType": "enum Types.TicketType",
        "name": "_ticketType",
        "type": "uint8"
      }
    ],
    "name": "EventOrganized",
    "type": "event"
  },
  {
    "anonymous": false,
    "inputs": [
      {
        "indexed": true,
        "internalType": "uint256",
        "name": "_eventId",
        "type": "uint256"
      },
      {
        "indexed": true,
        "internalType": "address",
        "name": "_organiser",
        "type": "address"
      },
      {
        "indexed": false,
        "internalType": "uint256",
        "name": "_amount",
        "type": "uint256"
      },
      {
        "indexed": false,
        "internalType": "uint256",
        "name": "_attendanceRate",
        "type": "uint256"
      },
      {
        "indexed": false,
        "internalType": "bool",
        "name": "_manuallyReleased",
        "type": "bool"
      }
    ],
    "name": "RevenueReleased",
    "type": "event"
  },
  {
    "anonymous": false,
    "inputs": [
      {
        "indexed": true,
        "internalType": "uint256",
        "name": "_eventId",
        "type": "uint256"
      },
      {
        "indexed": true,
        "internalType": "address",
        "name": "_organiser",
        "type": "address"
      },
      {
        "indexed": false,
        "internalType": "address",
        "name": "_ticketNFTAddr",
        "type": "address"
      },
      {
        "indexed": false,
        "internalType": "uint256",
        "name": "_ticketFee",
        "type": "uint256"
      },
      {
        "indexed": false,
        "internalType": "string",
        "name": "_ticketType",
        "type": "string"
      }
    ],
    "name": "TicketCreated",
    "type": "event"
  },
  {
    "anonymous": false,
    "inputs": [
      {
        "indexed": true,
        "internalType": "uint256",
        "name": "_eventId",
        "type": "uint256"
      },
      {
        "indexed": true,
        "internalType": "address",
        "name": "_buyer",
        "type": "address"
      },
      {
        "indexed": false,
        "internalType": "uint256",
        "name": "_ticketFee",
        "type": "uint256"
      }
    ],
    "name": "TicketPurchased",
    "type": "event"
  },
  {
    "inputs": [],
    "name": "FREE_TICKET_PRICE",
    "outputs": [
      {
        "internalType": "uint256",
        "name": "",
        "type": "uint256"
      }
    ],
    "stateMutability": "view",
    "type": "function"
  },
  {
    "inputs": [],
    "name": "MINIMUM_ATTENDANCE_RATE",
    "outputs": [
      {
        "internalType": "uint256",
        "name": "",
        "type": "uint256"
      }
    ],
    "stateMutability": "view",
    "type": "function"
  },
  {
    "inputs": [
      {
        "internalType": "uint256",
        "name": "_eventId",
        "type": "uint256"
      }
    ],
    "name": "canReleaseRevenue",
    "outputs": [
      {
        "internalType": "bool",
        "name": "canRelease",
        "type": "bool"
      },
      {
        "internalType": "uint256",
        "name": "attendanceRate",
        "type": "uint256"
      },
      {
        "internalType": "uint256",
        "name": "revenue",
        "type": "uint256"
      }
    ],
    "stateMutability": "view",
    "type": "function"
  },
  {
    "inputs": [
      {
        "internalType": "string",
        "name": "_title",
        "type": "string"
      },
      {
        "internalType": "string",
        "name": "_desc",
        "type": "string"
      },
      {
        "internalType": "string",
        "name": "_imageUri",
        "type": "string"
      },
      {
        "internalType": "string",
        "name": "_location",
        "type": "string"
      },
      {
        "internalType": "uint256",
        "name": "_startDate",
        "type": "uint256"
      },
      {
        "internalType": "uint256",
        "name": "_endDate",
        "type": "uint256"
      },
      {
        "internalType": "uint256",
        "name": "_expectedAttendees",
        "type": "uint256"
      },
      {
        "internalType": "enum Types.TicketType",
        "name": "_ticketType",
        "type": "uint8"
      }
    ],
    "name": "createEvent",
    "outputs": [
      {
        "internalType": "uint256",
        "name": "",
        "type": "uint256"
      }
    ],
    "stateMutability": "nonpayable",
    "type": "function"
  },
  {
    "inputs": [
      {
        "internalType": "uint256",
        "name": "_eventId",
        "type": "uint256"
      },
      {
        "internalType": "enum Types.PaidTicketCategory",
        "name": "_category",
        "type": "uint8"
      },
      {
        "internalType": "uint256",
        "name": "_ticketFee",
        "type": "uint256"
      },
      {
        "internalType": "string",
        "name": "_ticketUri",
        "type": "string"
      }
    ],
    "name": "createTicket",
    "outputs": [],
    "stateMutability": "nonpayable",
    "type": "function"
  },
  {
    "inputs": [
      {
        "internalType": "uint256",
        "name": "",
        "type": "uint256"
      }
    ],
    "name": "eventTickets",
    "outputs": [
      {
        "internalType": "bool",
        "name": "hasRegularTicket",
        "type": "bool"
      },
      {
        "internalType": "bool",
        "name": "hasVIPTicket",
        "type": "bool"
      },
      {
        "internalType": "uint256",
        "name": "regularTicketFee",
        "type": "uint256"
      },
      {
        "internalType": "uint256",
        "name": "vipTicketFee",
        "type": "uint256"
      },
      {
        "internalType": "address",
        "name": "regularTicketNFT",
        "type": "address"
      },
      {
        "internalType": "address",
        "name": "vipTicketNFT",
        "type": "address"
      }
    ],
    "stateMutability": "view",
    "type": "function"
  },
  {
    "inputs": [
      {
        "internalType": "uint256",
        "name": "",
        "type": "uint256"
      }
    ],
    "name": "events",
    "outputs": [
      {
        "internalType": "string",
        "name": "title",
        "type": "string"
      },
      {
        "internalType": "string",
        "name": "desc",
        "type": "string"
      },
      {
        "internalType": "string",
        "name": "imageUri",
        "type": "string"
      },
      {
        "internalType": "string",
        "name": "location",
        "type": "string"
      },
      {
        "internalType": "uint256",
        "name": "startDate",
        "type": "uint256"
      },
      {
        "internalType": "uint256",
        "name": "endDate",
        "type": "uint256"
      },
      {
        "internalType": "uint256",
        "name": "expectedAttendees",
        "type": "uint256"
      },
      {
        "internalType": "enum Types.TicketType",
        "name": "ticketType",
        "type": "uint8"
      },
      {
        "internalType": "enum Types.PaidTicketCategory",
        "name": "paidTicketCategory",
        "type": "uint8"
      },
      {
        "internalType": "uint32",
        "name": "userRegCount",
        "type": "uint32"
      },
      {
        "internalType": "uint32",
        "name": "verifiedAttendeesCount",
        "type": "uint32"
      },
      {
        "internalType": "uint256",
        "name": "ticketFee",
        "type": "uint256"
      },
      {
        "internalType": "address",
        "name": "ticketNFTAddr",
        "type": "address"
      },
      {
        "internalType": "address",
        "name": "organiser",
        "type": "address"
      }
    ],
    "stateMutability": "view",
    "type": "function"
  },
  {
    "inputs": [],
    "name": "getAllEvents",
    "outputs": [
      {
        "components": [
          {
            "internalType": "string",
            "name": "title",
            "type": "string"
          },
          {
            "internalType": "string",
            "name": "desc",
            "type": "string"
          },
          {
            "internalType": "string",
            "name": "imageUri",
            "type": "string"
          },
          {
            "internalType": "string",
            "name": "location",
            "type": "string"
          },
          {
            "internalType": "uint256",
            "name": "startDate",
            "type": "uint256"
          },
          {
            "internalType": "uint256",
            "name": "endDate",
            "type": "uint256"
          },
          {
            "internalType": "uint256",
            "name": "expectedAttendees",
            "type": "uint256"
          },
          {
            "internalType": "enum Types.TicketType",
            "name": "ticketType",
            "type": "uint8"
          },
          {
            "internalType": "enum Types.PaidTicketCategory",
            "name": "paidTicketCategory",
            "type": "uint8"
          },
          {
            "internalType": "uint32",
            "name": "userRegCount",
            "type": "uint32"
          },
          {
            "internalType": "uint32",
            "name": "verifiedAttendeesCount",
            "type": "uint32"
          },
          {
            "internalType": "uint256",
            "name": "ticketFee",
            "type": "uint256"
          },
          {
            "internalType": "address",
            "name": "ticketNFTAddr",
            "type": "address"
          },
          {
            "internalType": "address",
            "name": "organiser",
            "type": "address"
          }
        ],
        "internalType": "struct Types.EventDetails[]",
        "name": "",
        "type": "tuple[]"
      }
    ],
    "stateMutability": "view",
    "type": "function"
  },
  {
    "inputs": [],
    "name": "getAllEventsRegisteredFor",
    "outputs": [
      {
        "internalType": "uint256[]",
        "name": "",
        "type": "uint256[]"
      }
    ],
    "stateMutability": "view",
    "type": "function"
  },
  {
    "inputs": [],
    "name": "getAllValidEvents",
    "outputs": [
      {
        "internalType": "uint256[]",
        "name": "",
        "type": "uint256[]"
      }
    ],
    "stateMutability": "view",
    "type": "function"
  },
  {
    "inputs": [
      {
        "internalType": "uint256",
        "name": "_eventId",
        "type": "uint256"
      }
    ],
    "name": "getEvent",
    "outputs": [
      {
        "components": [
          {
            "internalType": "string",
            "name": "title",
            "type": "string"
          },
          {
            "internalType": "string",
            "name": "desc",
            "type": "string"
          },
          {
            "internalType": "string",
            "name": "imageUri",
            "type": "string"
          },
          {
            "internalType": "string",
            "name": "location",
            "type": "string"
          },
          {
            "internalType": "uint256",
            "name": "startDate",
            "type": "uint256"
          },
          {
            "internalType": "uint256",
            "name": "endDate",
            "type": "uint256"
          },
          {
            "internalType": "uint256",
            "name": "expectedAttendees",
            "type": "uint256"
          },
          {
            "internalType": "enum Types.TicketType",
            "name": "ticketType",
            "type": "uint8"
          },
          {
            "internalType": "enum Types.PaidTicketCategory",
            "name": "paidTicketCategory",
            "type": "uint8"
          },
          {
            "internalType": "uint32",
            "name": "userRegCount",
            "type": "uint32"
          },
          {
            "internalType": "uint32",
            "name": "verifiedAttendeesCount",
            "type": "uint32"
          },
          {
            "internalType": "uint256",
            "name": "ticketFee",
            "type": "uint256"
          },
          {
            "internalType": "address",
            "name": "ticketNFTAddr",
            "type": "address"
          },
          {
            "internalType": "address",
            "name": "organiser",
            "type": "address"
          }
        ],
        "internalType": "struct Types.EventDetails",
        "name": "eventDetails",
        "type": "tuple"
      }
    ],
    "stateMutability": "view",
    "type": "function"
  },
  {
    "inputs": [
      {
        "internalType": "uint256[]",
        "name": "_eventIds",
        "type": "uint256[]"
      }
    ],
    "name": "getEventsRequiringManualRelease",
    "outputs": [
      {
        "internalType": "uint256[]",
        "name": "eventIds",
        "type": "uint256[]"
      },
      {
        "internalType": "uint256[]",
        "name": "attendanceRates",
        "type": "uint256[]"
      },
      {
        "internalType": "uint256[]",
        "name": "revenues",
        "type": "uint256[]"
      }
    ],
    "stateMutability": "view",
    "type": "function"
  },
  {
    "inputs": [],
    "name": "getMyEvents",
    "outputs": [
      {
        "internalType": "uint256[]",
        "name": "",
        "type": "uint256[]"
      }
    ],
    "stateMutability": "view",
    "type": "function"
  },
  {
    "inputs": [],
    "name": "getMyTickets",
    "outputs": [
      {
        "internalType": "uint256[]",
        "name": "eventIds",
        "type": "uint256[]"
      },
      {
        "internalType": "string[]",
        "name": "ticketTypes",
        "type": "string[]"
      },
      {
        "internalType": "bool[]",
        "name": "verified",
        "type": "bool[]"
      }
    ],
    "stateMutability": "view",
    "type": "function"
  },
  {
    "inputs": [
      {
        "internalType": "address",
        "name": "",
        "type": "address"
      },
      {
        "internalType": "uint256",
        "name": "",
        "type": "uint256"
      }
    ],
    "name": "hasRegistered",
    "outputs": [
      {
        "internalType": "bool",
        "name": "",
        "type": "bool"
      }
    ],
    "stateMutability": "view",
    "type": "function"
  },
  {
    "inputs": [
      {
        "internalType": "address",
        "name": "",
        "type": "address"
      },
      {
        "internalType": "uint256",
        "name": "",
        "type": "uint256"
      }
    ],
    "name": "isVerified",
    "outputs": [
      {
        "internalType": "bool",
        "name": "",
        "type": "bool"
      }
    ],
    "stateMutability": "view",
    "type": "function"
  },
  {
    "inputs": [
      {
        "internalType": "bytes[]",
        "name": "data",
        "type": "bytes[]"
      }
    ],
    "name": "multicall",
    "outputs": [
      {
        "internalType": "bytes[]",
        "name": "results",
        "type": "bytes[]"
      }
    ],
    "stateMutability": "nonpayable",
    "type": "function"
  },
  {
    "inputs": [],
    "name": "owner",
    "outputs": [
      {
        "internalType": "address payable",
        "name": "",
        "type": "address"
      }
    ],
    "stateMutability": "view",
    "type": "function"
  },
  {
    "inputs": [
      {
        "internalType": "uint256",
        "name": "_eventId",
        "type": "uint256"
      },
      {
        "internalType": "enum Types.PaidTicketCategory",
        "name": "_category",
        "type": "uint8"
      },
      {
        "internalType": "address[]",
        "name": "_recipients",
        "type": "address[]"
      }
    ],
    "name": "purchaseMultipleTickets",
    "outputs": [],
    "stateMutability": "payable",
    "type": "function"
  },
  {
    "inputs": [
      {
        "internalType": "uint256",
        "name": "_eventId",
        "type": "uint256"
      },
      {
        "internalType": "enum Types.PaidTicketCategory",
        "name": "_category",
        "type": "uint8"
      }
    ],
    "name": "purchaseTicket",
    "outputs": [],
    "stateMutability": "payable",
    "type": "function"
  },
  {
    "inputs": [
      {
        "internalType": "uint256",
        "name": "_eventId",
        "type": "uint256"
      }
    ],
    "name": "releaseRevenue",
    "outputs": [],
    "stateMutability": "nonpayable",
    "type": "function"
  },
  {
    "inputs": [],
    "name": "totalEventOrganised",
    "outputs": [
      {
        "internalType": "uint256",
        "name": "",
        "type": "uint256"
      }
    ],
    "stateMutability": "view",
    "type": "function"
  },
  {
    "inputs": [],
    "name": "totalPurchasedTicket",
    "outputs": [
      {
        "internalType": "uint256",
        "name": "",
        "type": "uint256"
      }
    ],
    "stateMutability": "view",
    "type": "function"
  },
  {
    "inputs": [],
    "name": "totalTicketCreated",
    "outputs": [
      {
        "internalType": "uint256",
        "name": "",
        "type": "uint256"
      }
    ],
    "stateMutability": "view",
    "type": "function"
  },
  {
    "inputs": [
      {
        "internalType": "uint256",
        "name": "_eventId",
        "type": "uint256"
      }
    ],
    "name": "verifyAttendance",
    "outputs": [],
    "stateMutability": "nonpayable",
    "type": "function"
  },
  {
    "inputs": [
      {
        "internalType": "uint256",
        "name": "_eventId",
        "type": "uint256"
      },
      {
        "internalType": "address[]",
        "name": "_attendees",
        "type": "address[]"
      }
    ],
    "name": "verifyGroupAttendance",
    "outputs": [],
    "stateMutability": "nonpayable",
    "type": "function"
  },
  {
    "stateMutability": "payable",
    "type": "receive"
  }
]
